MANIFEST.in
README.md
setup.py
bin/tvgg
tvguidegen/__init__.py
tvguidegen.egg-info/PKG-INFO
tvguidegen.egg-info/SOURCES.txt
tvguidegen.egg-info/dependency_links.txt
tvguidegen.egg-info/not-zip-safe
tvguidegen.egg-info/requires.txt
tvguidegen.egg-info/top_level.txt
tvguidegen/m3u/__init__.py
tvguidegen/m3u/tools.py
tvguidegen/model/__init__.py
tvguidegen/model/collections.py
tvguidegen/processors/__init__.py
tvguidegen/processors/xmltv.py
tvguidegen/scripts/__init__.py
tvguidegen/scripts/importm3u.py