Metadata-Version: 1.0
Name: tvguidegen
Version: 0.2.4
Summary: TV Guide Generator
Home-page: https://github.com/7jtv/tvguidegen
Author: Kas IPTV
Author-email: kas.iptv@gmail.com
License: MIT
Platform: UNKNOWN
